tests/__init__.py
tests/conftest.py
tests/test_helpers.py
tests/test_viraloverlay.py
viraloverlay/__init__.py
viraloverlay/config.py
viraloverlay/custom_types.py
viraloverlay/exceptions.py
viraloverlay/helpers.py
viraloverlay/viraloverlay.py
viraloverlay/vo.py
viraloverlay-0.178.dist-info/METADATA
viraloverlay-0.178.dist-info/WHEEL
viraloverlay-0.178.dist-info/entry_points.txt
viraloverlay-0.178.dist-info/top_level.txt
viraloverlay-0.178.dist-info/RECORD
