Metadata-Version: 2.1
Name: viraloverlay
Version: 0.178
Summary: A CLI to create videos overlaid with text.
Home-page: https://github.com/zevaverbach/viraloverlay
License: UNKNOWN
Platform: UNKNOWN
Requires-Dist: Click
